{
  "menuItems": [
    {
      "id": 1,
      "parentId": 7,
      "name": "Traditional Breakfast Set",
      "description": "Omlette, sour cream, sausages, cream, \ncheese, honey, butter, cucumber, tomato, tea, \ncoffe or fresh juice",
      "imageName": "i2_1.png",
      "descLineCount": 3, 
      "headLineCount": 1,
      "imageCollection":["2_1.png"],
      "price": 79,
      "hasChield": false,
      "chields": []
    },
    {
      "id": 2,
      "parentId": 7,
      "name": "Omlettes:",
      "description": "",
      "imageName": "i2_2.png",
      "imageCollection":["2.jpg","2_1.jpg","2_2.jpg","2_3.jpg"],
      "descLineCount": 1,
      "headLineCount": 1,
      "price": 0,
      "hasChield": true,
      "chields": [
        {
          "id": 1,
          "name": "Classic",
          "description":"Test description",
          "descLineCount": 1,
          "headLineCount": 1,
          "prices": [
            12
          ]
        },
        {
          "id": 2,
          "name": "With onion",
          "prices": [
            15
          ]
        },
        {
          "id": 3,
          "name": "With suchuk",
          "prices": [
            25
          ]
        },
        {
          "id": 4,
          "name": "With cheese",
          "prices": [
            17
          ]
        }
      ]
    },
    {
      "id": 3,
      "parentId": 7,
      "name": "Crepe:",
      "description": "",
      "imageName": "i2_3.png",
      "imageCollection":["3_1.jpg","3_2.jpg","3_3.jpg"],
      "descLineCount": 1,
      "headLineCount": 1,
      "price": 0,
      "hasChield": true,
      "chields": [
        {
          "id": 1,
          "name": "With meat",
          "prices": [
            20
          ]
        },
        {
          "id": 2,
          "name": "With cottage cheese",
          "prices": [
            15
          ]
        },
        {
          "id": 3,
          "name": "With nutella",
          "prices": [
            17
          ]
        },
        {
          "id": 4,
          "name": "With jam",
          "prices": [
            15
          ]
        }
      ]
    },
    {
      "id": 4,
      "parentId": 7,
      "name": "Sabzi Kuku",
      "description": "Sizzling Greens Omelet, Served with \nPlain Yogurt and Grated Walnuts",
      "imageName": "i2_4.png",
      "descLineCount": 2,
      "imageCollection":["4.jpg"],
      "headLineCount": 1,
      "price": 35,
      "hasChield": false,
      "chields": []
    },
    {
      "id": 5,
      "parentId": 7,
      "name": "Yumurta- Pomidor",
      "description": "Azeri Style Shakshuka - Finely cut, Fresh \nPeeled Organic Tomatoes imported from \nAzerbaijan, Fried with Egg and Butter",
      "imageName": "i2_5.png",
      "imageCollection":["2_5.png"],
      "descLineCount": 3,
      "headLineCount": 1,
      "price": 39,
      "hasChield": false,
      "chields": []
    },
    {
      "id": 6,
      "parentId": 1,
      "name": "Chicken",
      "description": "Chicken meat, Carrot, Mix Capsicum, onion, \nnoodles, potato and butter",
      "imageName": "i3_1.png",
      "descLineCount": 2,
      "imageCollection":["3_1.png"],
      "headLineCount": 1,
      "price": 19,
      "hasChield": false,
      "chields": []
    },
    {
      "id": 7,
      "parentId": 1,
      "name": "Dushbara",
      "description": "Traditional Lamb Dumpling Soup served with \nGarlic and Dry Mint Vinegar. \nOrganic Lamb Import from Azerbaijan.",
      "imageName": "i3_2.png",
      "descLineCount": 3,
      "imageCollection":["7.jpg"],
      "headLineCount": 1,
      "price": 32,
      "hasChield": false,
      "chields": []
    },
    {
      "id": 8,
      "parentId": 1,
      "name": "Dovga",
      "description": "Yogurt Soup Cooked with Mixed Greens, \nMountain Herbs,Peas and Rice. Dovga is \noften served warm in a bowl during winters \nor refreshingly cold in glass during summers.",
      "imageName": "i3_3.png",
      "imageCollection":["8.jpeg"],
      "descLineCount": 4,
      "headLineCount": 1,
      "price": 24,
      "hasChield": false,
      "chields": []
    },
    {
      "id": 9,
      "parentId": 4,
      "name": "Mangal Salad",
      "description": "Grilled and Peeled Eggplant, Peppers and \nTomatoes, Mixed with Olive Oil, Finely Cut \nBasil, Garlic, Parsley and Red Onion ",
      "imageName": "i4_1.png",
      "imageCollection":["9.jpg"],
      "descLineCount": 3,
      "headLineCount": 1,
      "price": 22,
      "hasChield": false,
      "chields": []
    },
    {
      "id": 10,
      "parentId": 4,
      "name": "Choban Salad",
      "description": "Finely cut Cucumbers, Tomatoes, Red Onions, \nDill, Red Basil, Coriander, mixed with \nFresh Lemon Juice and Olive Oil",
      "imageName": "i4_2.png",
      "descLineCount": 3,
      "headLineCount": 1,
      "imageCollection":["10.jpg"],
      "price": 19,
      "hasChield": false,
      "chields": []
    },
    {
      "id": 11,
      "parentId": 4,
      "name": "Cesar",
      "description": "Chicken breast, iceberg,  lollorosso, cherry \ntomato parmesan cheese and special sauce",
      "imageName": "i4_3.png",
      "descLineCount": 2,
      "headLineCount": 1,
      "imageCollection":["11.jpg"],
      "price": 39,
      "hasChield": false,
      "chields": []
    },
    {
      "id": 13,
      "parentId": 4,
      "name": "Yashil Salad",
      "description": "Sundried tomato, shallot onion, Lollo Rosso, \nrucola salad, leaf salad, Ginger and lemon sauce",
      "imageName": "i4_5.png",
      "imageCollection":["13.jpg"],
      "descLineCount": 2,
      "headLineCount": 1,
      "price": 28,
      "hasChield": false,
      "chields": []
    },
    {
      "id": 14,
      "parentId": 2,
      "name": "Turshu Govurma Pilaw",
      "description": "Organic lamb import from Azerbaijan, Chestnuts \nwith Dried Fruits fried with Butter and Onion, \nserved with Saffron Rice",
      "imageName": "i5_1.png",
      "descLineCount": 3,
      "headLineCount": 1,
      "imageCollection":["14.jpg"],
      "price": 72,
      "hasChield": false,
      "chields": []
    },
    {
      "id": 15,
      "parentId": 2,
      "name": "Baku Style Govurma",
      "description": "Lamb ,Potato , red onion, butter, sumakh with \ngreen. Organic Lamb Import from Azerbaijan",
      "imageName": "i5_2.png",
      "descLineCount": 2,
      "imageCollection":["5_2.png"],
      "headLineCount": 1,
      "price": 65,
      "hasChield": false,
      "chields": []
    },
    {
      "id": 16,
      "parentId": 2,
      "name": "Xamalı Toyuq",
      "description": "Chicken fillet, mushroom, onion, pickled \ncucumber, tomato, cream, served with rice.",
      "imageName": "78.png",
      "descLineCount": 2,
      "imageCollection":["16_1.jpeg"],
      "headLineCount": 1,
      "price": 59,
      "hasChield": false,
      "chields": []
    },
    
    
    {
      "id": 19,
      "parentId": 3,
      "name": "Lamb Lula Kebab(250g)",
      "description": "Prepared with Minced Lamb, Onions and Greens.\nOrganic Lamb Import from Azerbaijan. ",
      "imageName": "i6_1.png",
      "descLineCount": 2,
      "headLineCount": 1,
      "imageCollection":["6_1.png"],
      "price": 75,
      "hasChield": false,
      "chields": []
    },
    {
      "id": 20,
      "parentId": 3,
      "name": "Potato Lula Kebab(250g)",
      "description": "Mashed Potato Kebab with Lamb fat.",
      "imageName": "i6_2.png",
      "descLineCount": 1,
      "imageCollection":["20.jpeg"],
      "headLineCount": 1,
      "price": 39,
      "hasChield": false,
      "chields": []
    },
    {
      "id": 21,
      "parentId": 3,
      "name": "Chicken Tike Kebab(300g)",
      "description": "Chicken marinated with tomato sauce \nand spices",
      "imageName": "i6_3_.png",
      "imageCollection":["21.jpg","21_1.jpeg"],
      "descLineCount": 2,
      "headLineCount": 1,
      "price": 59,
      "hasChield": false,
      "chields": []
    },
    {
      "id": 22,
      "parentId": 3,
      "name": "Lamb Tike Kebab(250g)",
      "description": "Lamb marinated with onion and lemon juice. \nImportant from Azerbaijan",
      "imageName": "i6_4.png",
      "descLineCount": 2,
      "imageCollection":["22.jpeg"],
      "headLineCount": 1,
      "price": 79,
      "hasChield": false,
      "chields": []
    },
    {
      "id": 23,
      "parentId": 3,
      "name": "Lamb Ribs Kebab(450g)",
      "description": "Only fresh pepper and sea salt. Lamb \nimportant from Azerbaijan",
      "imageName": "i6_5.png",
      "descLineCount": 2,
      "headLineCount": 1,
      "imageCollection":["23.jpeg"],
      "price": 89,
      "hasChield": false,
      "chields": []
    },
    {
      "id": 24,
      "parentId": 8,
      "name": "Fruit Platter",
      "description": "Assorted cut fruit in Azeri style",
      "imageName": "i7_1.png",
      "descLineCount": 1,
      "imageCollection":["24.jpg"],
      "headLineCount": 1,
      "price": 50,
      "hasChield": false,
      "chields": []
    },
    {
      "id": 25,
      "parentId": 8,
      "name": "Baklava with Ice Cream",
      "description": "",
      "imageName": "i7_2.png",
      "descLineCount": 1,
      "headLineCount": 1,
      "imageCollection":["25.jpg"],
      "price": 39,
      "hasChield": false,
      "chields": []
    },
    {
      "id": 26,
      "parentId": 8,
      "name": "Murabba",
      "description": "Homemade Murabbas, free of concentrate \nand chemical additives. Naturally prepared \nwith Fruits preserved in Sugar Syrup  Walnut \n Yellow Cherries \n Green Olives \n Watermelon \n Quince \n Strawberry \n Apricot FIGS",
      "imageName": "i7_3.png",
      "descLineCount": 9,
      "headLineCount": 1,
      "imageCollection":["26.jpg","26_1.jpeg"],
      "price": 25,
      "hasChield": false,
      "chields": []
    },
    {
      "id": 27,
      "parentId": 8,
      "name": "Ice Cream",
      "description": "Strawberry \n Vanilla \n Chocolate",
      "imageName": "i7_4.png",
      "imageCollection":["7_4.png","27_1.jpeg"],
      "descLineCount": 3,
      "headLineCount": 1,
      "price": 30,
      "hasChield": false,
      "chields": []
    },
    {
      "id": 28,
      "parentId": 9,
      "name": "Drinks",
      "description": "Coca Cola \nCocoa Cola Light \nFanta \nSprite",
      "imageName": "image.png",
      "descLineCount": 4,
      "headLineCount": 1,
      "price": 12,
      "hasChield": false,
      "chields": []
    },
    {
      "id": 29,
      "parentId": 9,
      "name": "Still Water",
      "description": "",
      "imageName": "image.png",
      "descLineCount": 1,
      "headLineCount": 1,
      "price": 0,
      "hasChield": true,
      "chields": [
        {
          "id": 1,
          "name": "330 ml",
          "prices": [
            12
          ]
        },
        {
          "id": 1,
          "name": "750 ml",
          "prices": [
            20
          ]
        }
      ]
    },
    {
      "id": 30,
      "parentId": 9,
      "name": "Sparkling Water",
      "description": "",
      "imageName": "image.png",
      "descLineCount": 1,
      "headLineCount": 1,
      "price": 0,
      "hasChield": true,
      "chields": [
        {
          "id": 1,
          "name": "330 ml",
          "prices": [
            15
          ]
        },
        {
          "id": 1,
          "name": "750 ml",
          "prices": [
            25
          ]
        }
      ]
    },
    {
      "id": 31,
      "parentId": 9,
      "name": "Compote (1 litre)",
      "description": "",
      "imageName": "i8_4.png",
      "imageCollection":["8_4.png"],
      "descLineCount": 1,
      "headLineCount": 1,
      "price": 45,
      "hasChield": false,
      "chields": []
    },
    {
      "id": 32,
      "parentId": 9,
      "name": "Bitter Lemon ",
      "description": "",
      "imageName": "image.png",
      "descLineCount": 1,
      "headLineCount": 1,
      "price": 20,
      "hasChield": false,
      "chields": []
    },
    {
      "id": 33,
      "parentId": 10,
      "name": "Rice",
      "description": "",
      "imageName": "image.png",
      "descLineCount": 1,
      "headLineCount": 1,
      "price": 15,
      "hasChield": false,
      "chields": []
    },
    {
      "id": 34,
      "parentId": 10,
      "name": "French fries",
      "description": "",
      "imageName": "image.png",
      "descLineCount": 1,
      "headLineCount": 1,
      "price": 15,
      "hasChield": false,
      "chields": []
    },
    {
      "id": 35,
      "parentId": 10,
      "name": "Mash potato",
      "description": "",
      "imageName": "image.png",
      "descLineCount": 1,
      "headLineCount": 1,
      "price": 20,
      "hasChield": false,
      "chields": []
    },
    {
      "id": 36,
      "parentId": 10,
      "name": "Grilled vegetables",
      "description": "",
      "imageName": "image.png",
      "descLineCount": 1,
      "headLineCount": 1,
      "price": 25,
      "hasChield": false,
      "chields": []
    },
    {
      "id": 37,
      "parentId": 5,
      "name": "Chicken fillet deep fried",
      "description": "",
      "imageName": "i10_1.png",
      "descLineCount": 1,
      "headLineCount": 1,
      "imageCollection":["37.jpg"],
      "price": 29,
      "hasChield": false,
      "chields": []
    },
    {
      "id": 38,
      "parentId": 5,
      "name": "Chicken on chopstick",
      "description": "",
      "imageName": "i10_2.png",
      "descLineCount": 1,
      "imageCollection":["38.jpg"],
      "headLineCount": 1,
      "price": 32,
      "hasChield": false,
      "chields": []
    },
   
    {
      "id": 40,
      "parentId": 6,
      "name": "Shah Plov",
      "description": "Preorder.\nGood for 2 people. Rice, lamb, chestnut, dried \nfruits, saffron all these wrapped in thin pita bread.\nOrganic lamb import from Azerbaijan",
      "imageName": "i11_2.png",
      "descLineCount": 4,
      "headLineCount": 1,
      "imageCollection":["11_2.png"],
      "price": 189,
      "hasChield": false,
      "chields": []
    },
    {
      "id": 42,
      "parentId": 6,
      "name": "Quzu Budu Sobada",
      "description": "Preorder.\nGood for 4 person. Whole marinated lamb leg \nwith garlic andcarrot. Wrapped in thin bread. \nServed with vegetable.Organic lamb import\n from Azerbaijan",
      "imageName": "i11_4.png",
      "descLineCount": 5,
      "headLineCount": 1,
      "imageCollection":["42.jpg"],
      "price": 365,
      "hasChield": false,
      "chields": []
    },
    
    {
      "id": 44,
      "parentId": 4,
      "name": "Vegetable Bouquet",
      "description": "Organic Tomato and Cucumber with 4 kind of \ngreens organic import from Azerbaijan",
      "imageName": "i12_1.png",
      "descLineCount": 2,
      "imageCollection":["44.JPG"],
      "headLineCount": 1,
      "price": 35,
      "hasChield": false,
      "chields": []
    },
    {
      "id": 45,
      "parentId": 4,
      "name": "Cheese Platter(200g)",
      "description": "Cheese brinza, smoked cheese, cheese motal \nspecial from Azerbaijan",
      "imageName": "i12_2.png",
      "imageCollection":["45.jpg"],
      "descLineCount": 2,
      "headLineCount": 1,
      "price": 29,
      "hasChield": false,
      "chields": []
    },
    {
      "id": 46,
      "parentId": 4,
      "name": "Assorted Pickles",
      "description": "Assorted homemade Fruit & Vegetable Pickles; \nImported from different villages of Azerbaijan",
      "imageName": "i12_3.png",
      "descLineCount": 2,
      "imageCollection":["46.JPG"],
      "headLineCount": 1,
      "price": 22,
      "hasChield":false,
      "chields": []
    },
    {
      "id": 47,
      "parentId": 4,
      "name": "Deep Fried Gurza",
      "description": "Deep fried dumplings filled with Lamb and Onion;\nServed with Sour Cream. Organic Lamb \nImport from Azerbaijan.",
      "imageName": "i12_4.png",
      "descLineCount": 3,
      "headLineCount": 1,
      "imageCollection":["47.JPG"],
      "price": 32,
      "hasChield": false,
      "chields": []
    },
    {
      "id": 48,
      "parentId": 4,
      "name": "Gutab",
      "description": "",
      "imageName": "i12_5_.png",
      "descLineCount": 1,
      "headLineCount": 1,
      "imageCollection":["48.JPG","48_1.jpg"],
      "price": 139,
      "hasChield": true,
      "chields": [
        {
          "id": 1,
          "name": "With meat (1 piece)",
          "prices": [
            19
          ]
        },
        {
          "id": 2,
          "name": "With green (1 piece)",
          "prices": [
            15
          ]
        }
      ]
    },
    {
      "id": 49,
      "parentId": 6,
      "name": "Ribs Tandoor",
      "description": "Preorder.\nGood for 3 person. Whole marinated with \ngarlic and pomegranate souse served \nwith Vegetables.Organic Lamb Import \nfrom Azerbaijan.",
      "imageName": "i14_1_2.png",
      "descLineCount": 5,
      "imageCollection":["49_1.jpeg"],
      "headLineCount": 1,
      "price": 249,
      "hasChield": false,
      "chields": []
    },
   
    {
      "id": 51,
      "parentId": 8,
      "name": "Samovar Chai",
      "description": "Traditional tea set with assorted nuts, dry \nfruits, murabba of your choice. Azeri pastries \nand a Somovar Of Tea",
      "imageName": "i15_1.png",
      "descLineCount": 3,
      "imageCollection":["51.jpg","51_1.jpg"],
      "headLineCount": 1,
      "price": 125,
      "hasChield": false,
      "chields": []
    },
    {
      "id": 52,
      "parentId": 8,
      "name": "Chai (Tea pots)",
      "description": "Special Jag Chai\nFresh Plain Chai\nCardamom Chai\nChai with Ginger\nKeklik Oty Chai\nClove Chai\nJasmine Chai\nCinnamon Chai\nDry Mint Chai\nFresh Mint Green Chai",
      "imageName": "i15_2.png",
      "descLineCount": 10,
       "imageCollection":["15_2.png"],
      "headLineCount": 1,
      "price": 30,
      "hasChield": false,
      "chields": []
    },
    {
      "id": 53,
      "parentId": 8,
      "name": "Coffees",
      "description": "",
      "imageName": "image.png",
      "descLineCount": 1,
      "headLineCount": 1,
      "price": 0,
      "hasChield": true,
      "chields": [
        {
          "id": 1,
          "name": "Turkish Coffee (double)",
          "prices": [
            20,
            15
          ]
        },
        {
          "id": 2,
          "name": "Espresso (double)",
          "prices": [
            15,
            18
          ]
        },
        {
          "id": 3,
          "name": "Cappuccino",
          "prices": [
            25
          ]
        },
        {
          "id": 4,
          "name": "Coffee Latte",
          "prices": [
            25
          ]
        },
        {
          "id": 5,
          "name": "Latte with Caramel",
          "prices": [
            30
          ]
        },
        {
          "id": 6,
          "name": "Mocha",
          "prices": [
            25
          ]
        },
        {
          "id": 7,
          "name": "Hot Chocolate",
          "prices": [
            22
          ]
        },
        {
          "id": 8,
          "name": "Iced Mocha",
          "prices": [
            30
          ]
        }
      ]
    },
    {
      "id": 54,
      "parentId": 3,
      "name": "Adana Lula Kebab(250g)",
      "description": "Prepared with minced lamb, onions and red \nchili, Organic lamb import from Azerbaijan",
      "imageName": "i16_1.png",
      "descLineCount": 2,
      "headLineCount": 1,
      "imageCollection":["54.jpg"],
      "price": 75,
      "hasChield": false,
      "chields": []
    },
    {
      "id": 55,
      "parentId": 3,
      "name": "Mixed Grill (1750g)\nGood for 4 person",
      "description": "Lula Lamb Kebab, Adana Kebab, Lamb Rib \nKebab. Lamb Tikka kebab, Chicken Tikka Kebab,\nPotato Lula Kebab, Organic lamb import \nfrom Azerbaijan.",
      "imageName": "i16_2.png",
      "descLineCount": 4,
      "imageCollection":["55.jpeg"],
      "headLineCount": 2,
      "price": 369,
      "hasChield": false,
      "chields": []
    },
    {
      "id": 56,
      "parentId": 3,
      "name": "JAG Kebab(200g)",
      "description": "Traditional Turkish Erzurum kebab made of\nmarinated lamb with rice. Organic Lamb \nImport from Azerbaijan.",
      "imageName": "i16_3_.png",
      "descLineCount": 3,
      "headLineCount": 1,
      "imageCollection":["56.jpg","56_1.jpeg","56_2.jpeg"],
      "price": 65,
      "hasChield": false,
      "chields": []
    },
    
    {
      "id": 58,
      "parentId": 3,
      "name": "Chicken BBQ",
      "description": "Organic Chicken import from Azerbaijan \nserved with Fries",
      "imageName": "i13_2.png",
      "descLineCount": 2,
      "headLineCount": 1,
      "imageCollection":["73.jpeg"],
      "price": 72,
      "hasChield": false,
      "chields": []
    },
    {
      "id": 59,
      "parentId": 9,
      "name": "Ginger Ale",
      "description": "",
      "imageName": "image.png",
      "descLineCount": 1,
      "headLineCount": 1,
      "price": 20,
      "hasChield": false,
      "chields": []
    },
     
     
    {
      "id": 62,
      "parentId": 9,
      "name": "Lemonade (Georgia)",
      "description": "Tarragon\nPear\nLemon\nGrape",
      "imageName": "image.png",
      "descLineCount": 4,
      "headLineCount": 1,
      "price": 28,
      "hasChield": false,
      "chields": []
    },
    {
      "id": 63,
      "parentId": 9,
      "name": "Homemade Ice Tea",
      "description": "Lemon\nPeach",
      "imageName": "image.png",
      "descLineCount": 2,
      "headLineCount": 1,
      "price": 30,
      "hasChield": false,
      "chields": []
    },
     
    {
      "id": 65,
      "parentId": 9,
      "name": "Ayran",
      "description": "Azerbaijani Laban. Prepared simple or with Dry Mint",
      "imageName": "i65_1.png",
      "imageCollection":["65_1.jpeg"],
      "descLineCount": 1,
      "headLineCount": 1,
      "price": 22,
      "hasChield": false,
      "chields": []
    },
    {
      "id": 66,
      "parentId": 9,
      "name": "Doghramaj",
      "description": "Laban with Cucumber, Basil, Coriander and \nGreen Onion Leaves",
      "imageName": "image.png",
      "descLineCount": 2,
      "headLineCount": 1,
      "price": 19,
      "hasChield": false,
      "chields": []
    },
    {
      "id": 67,
      "parentId": 9,
      "name": "Fresh Squeezed:",
      "description": "",
      "imageName": "i67_.png",
      "descLineCount": 1,
      "headLineCount": 1,
      "imageCollection":["67_.jpg"],
      "price": 0,
      "hasChield": true,
      "chields": [
        {
          "id": 1,
          "name": "Apple",
          "prices": [
            25
          ]
        },
        {
          "id": 2,
          "name": "Orange",
          "prices": [
            25
          ]
        },
        {
          "id": 3,
          "name": "Carrot",
          "prices": [
            25
          ]
        },
        {
          "id": 4,
          "name": "Pineapple",
          "prices": [
            25
          ]
        },
        {
          "id": 5,
          "name": "Lemonade",
          "prices": [
            25
          ]
        },
        {
          "id": 6,
          "name": "Lemon and Mint",
          "prices": [
            25
          ]
        },
        {
          "id": 7,
          "name": "Pomegranate",
          "prices": [
            35
          ]
        }
      ]
    },
    
    {
      "id": 69,
      "parentId": 9,
      "name": "Sober Mojito",
      "description": "Non Alcoholic drink with Mint Leaves, \nCrushed Ice, Lime and Soda, mixed \nwith Fruit Syrup",
      "imageName": "i18_4_.PNG",
      "imageCollection":["69.jpg"],
      "descLineCount": 3,
      "headLineCount": 1,
      "price": 35,
      "hasChield": false,
      "chields": []
    },
    {
      "id": 70,
      "parentId": 9,
      "name": "Cinderella",
      "description": "Pineapple Juice, Orange Juice, Lemon Juice, \nGrenadine Syrup",
      "imageName": "image.png",
      "descLineCount": 2,
      "headLineCount": 1,
      "price": 35,
      "hasChield": false,
      "chields": []
    },
    {
      "id": 71,
      "parentId": 9,
      "name": "Milkshakes:",
      "description": "Strawberry\nBanana\nVanilla\nChocolate\nOreo",
      "imageName": "i19_4.png",
      "descLineCount": 5,
      "headLineCount": 1,
      "imageCollection":["71.jpg"],
      "price": 39,
      "hasChield": false,
      "chields": []
    },
    {
      "id": 72,
      "parentId": 2,
      "name": "Gurza",
      "description": "Steamed Lamb dumplings in Azeri style,\nserved with Sour Cream. Organic Lamb Import \nfrom Azerbaijan.",
      "imageName": "i13_1.png",
      "descLineCount": 3,
      "headLineCount": 1,
      "imageCollection":["72.jpg"],
      "price": 59,
      "hasChield": false,
      "chields": []
    },
    {
      "id": 73,
      "parentId": 2,
      "name": "Chicken Tabaka",
      "description": "Fried Organic Baby Chicken with\n home stile potato",
      "imageName": "i13_2.png",
      "descLineCount": 2,
      "headLineCount": 1,
      "imageCollection":["73.jpeg"],
      "price": 72,
      "hasChield": false,
      "chields": []
    },
    {
      "id": 74,
      "parentId": 2,
      "name": "Saj",
      "description": "Cooked on Azeri style wok pan. \nServed with eggplant, potato, tomato, \npepper, onion, with your choice of.",
      "imageName":"i13_3.png",
      "descLineCount": 3,
      "headLineCount": 1,
      "imageCollection":["74_1.jpg","74_2.jpg"],
      "price": 35,
      "hasChield": true,
      "chields": [
        {
          "id": 1,
          "name": "Chicken(500g)",
          "prices": [159]
        },
        {
          "id": 2,
          "name": "Lamb(500g)",
          "prices": [175]
        },
        {
          "id": 3,
          "name": "Mix(750g)",
          "prices": [197]
        }
      ]
    },



    {
      "id": 75,
      "parentId": 8,
      "name": "Assorted Nuts & Dried Fruits",
      "description": "",
      "imageName": "i75_1.png",
      "descLineCount": 1,
      "headLineCount": 1,
      "imageCollection":["75_1.jpeg"],
      "price": 75,
      "hasChield": false,
      "chields": []
    }, 
    {
      "id": 77,
      "parentId": 8,
      "name": "Azəri Pakhlava(3pieces)",
      "description": "",
      "imageName": "i77_1.png",
      "descLineCount": 1,
      "headLineCount": 1,
      "imageCollection":["77_1.jpeg"],
      "price": 30,
      "hasChield": false,
      "chields": []
    }
  ]
}
